beneath/__init__.py
beneath/admin/__init__.py
beneath/admin/base.py
beneath/admin/client.py
beneath/admin/organizations.py
beneath/admin/projects.py
beneath/admin/secrets.py
beneath/admin/services.py
beneath/admin/tables.py
beneath/admin/users.py
beneath/beam/__init__.py
beneath/beam/convert_types.py
beneath/beam/read_from_beneath.py
beneath/beam/write_to_beneath.py
beneath/checkpointer.py
beneath/cli/__init__.py
beneath/cli/auth.py
beneath/cli/organization.py
beneath/cli/project.py
beneath/cli/service.py
beneath/cli/table.py
beneath/cli/utils.py
beneath/client.py
beneath/config.py
beneath/connection.py
beneath/consumer.py
beneath/cursor.py
beneath/easy.py
beneath/instance.py
beneath/job.py
beneath/pipeline/__init__.py
beneath/pipeline/base_pipeline.py
beneath/pipeline/parse_args.py
beneath/pipeline/pipeline.py
beneath/proto/__init__.py
beneath/proto/gateway.proto
beneath/proto/gateway_pb2.py
beneath/proto/gateway_pb2_grpc.py
beneath/schema.py
beneath/table.py
beneath/utils/__init__.py
beneath/utils/aiodelaybuffer.py
beneath/utils/aiopoller.py
beneath/utils/aioticker.py
beneath/utils/aioworkerpool.py
beneath/utils/identifiers.py
beneath/utils/infer_avro.py
beneath/writer.py
beneath-1.4.2.dist-info/entry_points.txt
beneath-1.4.2.dist-info/WHEEL
beneath-1.4.2.dist-info/METADATA
beneath-1.4.2.dist-info/RECORD
