Metadata-Version: 2.1
Name: beneath
Version: 1.4.2
Summary: Python client and CLI for Beneath (https://beneath.dev/)
Home-page: https://github.com/beneath-hq/beneath/tree/master/clients/python
License: MIT
Author: Beneath Systems
Author-email: hello@beneath.dev
Requires-Python: >=3.7,<4.0
Classifier: License :: OSI Approved :: MIT License
Classifier: Programming Language :: Python :: 3
Classifier: Programming Language :: Python :: 3.7
Classifier: Programming Language :: Python :: 3.8
Classifier: Programming Language :: Python :: 3.9
Requires-Dist: Cython (>=0.29.15,<0.30.0)
Requires-Dist: aiohttp (>=3.6.2,<4.0.0)
Requires-Dist: argparse (>=1.4,<2.0)
Requires-Dist: fastavro (>=1.0,<2.0)
Requires-Dist: grpcio (>=1.35.0,<2.0.0)
Requires-Dist: msgpack (>=1.0.0,<2.0.0)
Requires-Dist: pandas (>=1.0.1,<2.0.0)
Requires-Dist: protobuf (>=3.11.3,<4.0.0)
Requires-Dist: six (>=1.14.0,<2.0.0)
Project-URL: Documentation, https://python.docs.beneath.dev
Project-URL: Repository, https://github.com/beneath-hq/beneath/tree/master/clients/python
